subsnitch/__init__.py
subsnitch/__main__.py
subsnitch-0.0.1.dist-info/METADATA
subsnitch-0.0.1.dist-info/WHEEL
subsnitch-0.0.1.dist-info/entry_points.txt
subsnitch-0.0.1.dist-info/RECORD
