Metadata-Version: 2.1
Name: subsnitch
Version: 0.0.1
Summary: Python Boilerplate contains all the boilerplate you need to create a Python package.
Home-page: https://github.com/tbennett6421/subsnitch
Author: Tyler Bennett
Author-email: tbennett6421@gmail.com
Requires-Python: >=3.8.0,<3.12.0
Classifier: Environment :: Console
Classifier: Programming Language :: Python :: 3
Classifier: Programming Language :: Python :: 3.8
Classifier: Programming Language :: Python :: 3.9
Classifier: Programming Language :: Python :: 3.10
Classifier: Programming Language :: Python :: 3.11
Classifier: Topic :: Multimedia :: Sound/Audio
Requires-Dist: ffmpeg-python (>=0.2.0,<0.3.0)
Requires-Dist: moviepy (>=1.0.3,<2.0.0)
Project-URL: Repository, https://github.com/tbennett6421/subsnitch
